get_consecutive_filename/LICENSE
get_consecutive_filename/README.MD
get_consecutive_filename/__init__.py
get_consecutive_filename/requirements.txt
get_consecutive_filename/thirdparty.json
get_consecutive_filename-0.10.dist-info/LICENSE.rst
get_consecutive_filename-0.10.dist-info/METADATA
get_consecutive_filename-0.10.dist-info/WHEEL
get_consecutive_filename-0.10.dist-info/top_level.txt
get_consecutive_filename-0.10.dist-info/RECORD
